legal_doc_processing/__init__.py
legal_doc_processing/boot.py
legal_doc_processing/utils.py
legal_doc_processing/version.py
legal_doc_processing/base/__init__.py
legal_doc_processing/base/base.py
legal_doc_processing/base/data_handler.py
legal_doc_processing/base/predict_handler.py
legal_doc_processing/decision/__init__.py
legal_doc_processing/decision/decision.py
legal_doc_processing/decision/utils.py
legal_doc_processing/decision/information_extraction/__init__.py
legal_doc_processing/decision/information_extraction/code_law_violation.py
legal_doc_processing/decision/information_extraction/compliance_obligations.py
legal_doc_processing/decision/information_extraction/cooperation_credit.py
legal_doc_processing/decision/information_extraction/country_of_violation.py
legal_doc_processing/decision/information_extraction/court.py
legal_doc_processing/decision/information_extraction/currency.py
legal_doc_processing/decision/information_extraction/decision_date.py
legal_doc_processing/decision/information_extraction/defendant.py
legal_doc_processing/decision/information_extraction/extracted_authorities.py
legal_doc_processing/decision/information_extraction/extracted_sanctions.py
legal_doc_processing/decision/information_extraction/extracted_violations.py
legal_doc_processing/decision/information_extraction/folder.py
legal_doc_processing/decision/information_extraction/judge.py
legal_doc_processing/decision/information_extraction/justice_type.py
legal_doc_processing/decision/information_extraction/monetary_sanction.py
legal_doc_processing/decision/information_extraction/monitor.py
legal_doc_processing/decision/information_extraction/nature_de_sanction.py
legal_doc_processing/decision/information_extraction/nature_of_violations.py
legal_doc_processing/decision/information_extraction/penalty_details.py
legal_doc_processing/decision/information_extraction/reference.py
legal_doc_processing/decision/information_extraction/type.py
legal_doc_processing-2.2.6.dist-info/METADATA
legal_doc_processing-2.2.6.dist-info/WHEEL
legal_doc_processing-2.2.6.dist-info/top_level.txt
legal_doc_processing-2.2.6.dist-info/RECORD
