Metadata-Version: 2.1
Name: legal-doc-processing
Version: 2.2.6
Summary: Theolex document processing
Home-page: http://theolex-document-processing
Author: Jawad Alaoui
Author-email: jawad@theolex.io
License: MIT License
Keywords: theolex document processing package
Platform: UNKNOWN
Requires-Dist: pandas
Requires-Dist: nltk
Requires-Dist: transformers
Requires-Dist: spacy
Requires-Dist: tensorflow
Requires-Dist: clean-text
Requires-Dist: word2vec
Requires-Dist: dateparser
Requires-Dist: scikit-learn
Requires-Dist: google-cloud-storage
